proxybandit/__init__.py
proxybandit/core.py
proxybandit/gatherer.py
proxybandit/proxy.py
proxybandit/proxylist.py
proxybandit/data/sources.json
proxybandit-1.0.1.dist-info/LICENSE
proxybandit-1.0.1.dist-info/METADATA
proxybandit-1.0.1.dist-info/WHEEL
proxybandit-1.0.1.dist-info/top_level.txt
proxybandit-1.0.1.dist-info/RECORD
